[
  {
    "py/object": "model.contact.Contact",
    "firstname": "",
    "lastname": "",
    "id": null,
    "address": "",
    "all_phones_from_home_page": null,
    "homephone": "",
    "mobilephone": null,
    "workphone": null,
    "secondaryphone": null,
    "all_emails_from_home_page": null,
    "email": "",
    "email2": null,
    "email3": null
  },
  {
    "py/object": "model.contact.Contact",
    "firstname": "firstname",
    "lastname": "lastname1/?z",
    "id": null,
    "address": "addressLILR`2~P ce_d G4~ ,",
    "all_phones_from_home_page": null,
    "homephone": "homephoneY2GD 6.*5",
    "mobilephone": null,
    "workphone": null,
    "secondaryphone": null,
    "all_emails_from_home_page": null,
    "email": "email!tTlU]",
    "email2": null,
    "email3": null
  },
  {
    "py/object": "model.contact.Contact",
    "firstname": "firstname    ",
    "lastname": "lastname   /ih]",
    "id": null,
    "address": "addresshv5@F5?_,Ojze$ N$",
    "all_phones_from_home_page": null,
    "homephone": "homephonee,\"HK_|n",
    "mobilephone": null,
    "workphone": null,
    "secondaryphone": null,
    "all_emails_from_home_page": null,
    "email": "emailia,/ e%",
    "email2": null,
    "email3": null
  },
  {
    "py/object": "model.contact.Contact",
    "firstname": "firstnamep [!?",
    "lastname": "lastname= }wA",
    "id": null,
    "address": "address~O6",
    "all_phones_from_home_page": null,
    "homephone": "homephonev9xPG",
    "mobilephone": null,
    "workphone": null,
    "secondaryphone": null,
    "all_emails_from_home_page": null,
    "email": "emailZ#,.\\m ^= 1-",
    "email2": null,
    "email3": null
  },
  {
    "py/object": "model.contact.Contact",
    "firstname": "firstnameFqUJlN",
    "lastname": "lastname>",
    "id": null,
    "address": "address(  x $;` 6MJJ@r fjI",
    "all_phones_from_home_page": null,
    "homephone": "homephoneEM}u)F*",
    "mobilephone": null,
    "workphone": null,
    "secondaryphone": null,
    "all_emails_from_home_page": null,
    "email": "emailG' z5u2-aNZk)",
    "email2": null,
    "email3": null
  },
  {
    "py/object": "model.contact.Contact",
    "firstname": "firstname mJ ",
    "lastname": "lastnameA<C",
    "id": null,
    "address": "addressw>-UUCTNHseC;): Ur ",
    "all_phones_from_home_page": null,
    "homephone": "homephoneW_ @i",
    "mobilephone": null,
    "workphone": null,
    "secondaryphone": null,
    "all_emails_from_home_page": null,
    "email": "email",
    "email2": null,
    "email3": null
  }
]